{
  "type": "asset",
  "folder": "VGDM9gKIusGTm2DW",
  "name": "Smuggler 1",
  "system": {
    "requirement": "",
    "category": "Special Companion",
    "color": "#3d8b8a",
    "fields": [
      {
        "name": "Name",
        "value": ""
      }
    ],
    "abilities": [
      {
        "description": "<p>When you @Compendium[foundry-ironsworn.starforgedmoves.Item.05909d6310d209a6]{Make a Connection} to seek out a new contact in the underworld, the smuggler may assist. If they do, roll +their shadow and take +2 momentum on a hit. When a party member @Compendium[foundry-ironsworn.starforgedmoves.Item.3de42d2d3cb78855]{Sojourns} and scores a strong hit, the smuggler secures a valuable cache of a precious item or resource. One time only, the smuggler may use this acquisition to gain an automatic strong hit on any move where resources are a factor. If they do, take +3 momentum.</p>",
        "enabled": true,
        "hasClock": false,
        "clockMax": 4,
        "clockTicks": 0
      }
    ],
    "track": {
      "enabled": true,
      "name": "Health",
      "current": 0,
      "max": 5,
      "value": 5,
      "min": 0
    },
    "exclusiveOptions": [
      {
        "name": "Edge 2",
        "selected": false
      },
      {
        "name": "Heart 2",
        "selected": false
      },
      {
        "name": "Iron 1",
        "selected": false
      },
      {
        "name": "Shadow 3",
        "selected": false
      },
      {
        "name": "Wits 1",
        "selected": true
      }
    ],
    "conditions": [
      {
        "name": "Wounded",
        "ticked": false
      }
    ],
    "description": "<p>An expert in contraband and the underworld ways.</p>\n<p>Master Ability</p>"
  },
  "img": "modules/ancient-wonders/assets/iron-mask.svg",
  "effects": [],
  "ownership": {
    "default": 0,
    "MmM06BuCrG9h1GLg": 3
  },
  "flags": {
    "foundry-ironsworn": {
      "dfid": "Starforged/Assets/Companion/Banshee",
      "dsid": "asset:starforged/companion/banshee",
      "edit-mode": false
    }
  },
  "_stats": {
    "compendiumSource": null,
    "duplicateSource": null,
    "coreVersion": "13.351",
    "systemId": "foundry-ironsworn",
    "systemVersion": "1.25.3",
    "createdTime": 1746826729696,
    "modifiedTime": 1764466898016,
    "lastModifiedBy": "MmM06BuCrG9h1GLg",
    "exportSource": {
      "worldId": "starforged-development",
      "uuid": null,
      "coreVersion": "12.331",
      "systemId": "foundry-ironsworn",
      "systemVersion": "1.25.2"
    }
  },
  "_id": "IMVlT622yIoh4Wwc",
  "sort": 0,
  "_key": "!items!IMVlT622yIoh4Wwc"
}
