{
  "name": "Anomalous World Settlements - Expanse",
  "formula": "1d100",
  "description": "",
  "results": [
    {
      "range": [
        1,
        90
      ],
      "_id": "fkfr0ro3zW7u2UHR",
      "type": "text",
      "img": null,
      "weight": 1,
      "drawn": false,
      "flags": {},
      "_stats": {
        "coreVersion": "13.351",
        "systemId": null,
        "systemVersion": null,
        "createdTime": null,
        "modifiedTime": null,
        "lastModifiedBy": null,
        "compendiumSource": null,
        "duplicateSource": null,
        "exportSource": null
      },
      "description": "None",
      "name": "",
      "_key": "!tables.results!wUb0Qfky7Y3Z9eDE.fkfr0ro3zW7u2UHR"
    },
    {
      "range": [
        91,
        96
      ],
      "_id": "EXFTILxH5VIHdRT1",
      "type": "text",
      "img": null,
      "weight": 1,
      "drawn": false,
      "flags": {},
      "_stats": {
        "coreVersion": "13.351",
        "systemId": null,
        "systemVersion": null,
        "createdTime": null,
        "modifiedTime": null,
        "lastModifiedBy": null,
        "compendiumSource": null,
        "duplicateSource": null,
        "exportSource": null
      },
      "description": "Orbital",
      "name": "",
      "_key": "!tables.results!wUb0Qfky7Y3Z9eDE.EXFTILxH5VIHdRT1"
    },
    {
      "range": [
        97,
        100
      ],
      "_id": "A7rp6edf1wc6OGlv",
      "type": "text",
      "img": null,
      "weight": 1,
      "drawn": false,
      "flags": {},
      "_stats": {
        "coreVersion": "13.351",
        "systemId": null,
        "systemVersion": null,
        "createdTime": null,
        "modifiedTime": null,
        "lastModifiedBy": null,
        "compendiumSource": null,
        "duplicateSource": null,
        "exportSource": null
      },
      "description": "Grounded",
      "name": "",
      "_key": "!tables.results!wUb0Qfky7Y3Z9eDE.A7rp6edf1wc6OGlv"
    }
  ],
  "folder": "91H7T7JzC66KlbXd",
  "sort": 5,
  "_id": "wUb0Qfky7Y3Z9eDE",
  "img": "icons/svg/d20-grey.svg",
  "replacement": true,
  "displayRoll": true,
  "ownership": {
    "default": 0,
    "MmM06BuCrG9h1GLg": 3
  },
  "flags": {},
  "_stats": {
    "compendiumSource": null,
    "duplicateSource": null,
    "coreVersion": "13.351",
    "systemId": "foundry-ironsworn",
    "systemVersion": "1.25.1",
    "createdTime": 1745107454163,
    "modifiedTime": 1745107454163,
    "lastModifiedBy": "MmM06BuCrG9h1GLg",
    "exportSource": null
  },
  "_key": "!tables!wUb0Qfky7Y3Z9eDE"
}
