{
  "name": "Kintsugi World Settlements - Expanse",
  "formula": "1d100",
  "description": "",
  "results": [
    {
      "range": [
        1,
        93
      ],
      "_id": "8gMtkkNIWrEsJzOK",
      "type": "text",
      "img": null,
      "weight": 1,
      "drawn": false,
      "flags": {},
      "_stats": {
        "coreVersion": "13.351",
        "systemId": null,
        "systemVersion": null,
        "createdTime": null,
        "modifiedTime": null,
        "lastModifiedBy": null,
        "compendiumSource": null,
        "duplicateSource": null,
        "exportSource": null
      },
      "description": "None",
      "name": "",
      "_key": "!tables.results!qcddnRRXGcw0CBYA.8gMtkkNIWrEsJzOK"
    },
    {
      "range": [
        94,
        98
      ],
      "_id": "6Qss3G9kIeHFFj0F",
      "type": "text",
      "img": null,
      "weight": 1,
      "drawn": false,
      "flags": {},
      "_stats": {
        "coreVersion": "13.351",
        "systemId": null,
        "systemVersion": null,
        "createdTime": null,
        "modifiedTime": null,
        "lastModifiedBy": null,
        "compendiumSource": null,
        "duplicateSource": null,
        "exportSource": null
      },
      "description": "Orbital",
      "name": "",
      "_key": "!tables.results!qcddnRRXGcw0CBYA.6Qss3G9kIeHFFj0F"
    },
    {
      "range": [
        99,
        100
      ],
      "_id": "SUrMaMJodQ8Hqu25",
      "type": "text",
      "img": null,
      "weight": 1,
      "drawn": false,
      "flags": {},
      "_stats": {
        "coreVersion": "13.351",
        "systemId": null,
        "systemVersion": null,
        "createdTime": null,
        "modifiedTime": null,
        "lastModifiedBy": null,
        "compendiumSource": null,
        "duplicateSource": null,
        "exportSource": null
      },
      "description": "Grounded",
      "name": "",
      "_key": "!tables.results!qcddnRRXGcw0CBYA.SUrMaMJodQ8Hqu25"
    }
  ],
  "folder": "QYJDtxrcH8LiBWBc",
  "sort": 7,
  "_id": "qcddnRRXGcw0CBYA",
  "img": "icons/svg/d20-grey.svg",
  "replacement": true,
  "displayRoll": true,
  "ownership": {
    "default": 0,
    "MmM06BuCrG9h1GLg": 3
  },
  "flags": {},
  "_stats": {
    "compendiumSource": null,
    "duplicateSource": null,
    "coreVersion": "13.351",
    "systemId": "foundry-ironsworn",
    "systemVersion": "1.25.1",
    "createdTime": 1745897702899,
    "modifiedTime": 1745897702899,
    "lastModifiedBy": "MmM06BuCrG9h1GLg",
    "exportSource": null
  },
  "_key": "!tables!qcddnRRXGcw0CBYA"
}
