{
  "name": "Tidally-Locked World Dark Side - Metallic World",
  "formula": "1d100",
  "description": "<p>Use this table to reveal the planetary classes of each lateral band of a tidally-locked world. First, roll to determine the light side planetary class, then; roll on that column to define the dark side planetary class.</p>",
  "results": [
    {
      "range": [
        1,
        23
      ],
      "_id": "NNIqcHIujesDlsUK",
      "type": "text",
      "img": "icons/dice/d10black.svg",
      "weight": 1,
      "drawn": false,
      "flags": {},
      "_stats": {
        "coreVersion": "13.351",
        "systemId": null,
        "systemVersion": null,
        "createdTime": null,
        "modifiedTime": null,
        "lastModifiedBy": null,
        "compendiumSource": null,
        "duplicateSource": null,
        "exportSource": null
      },
      "description": "&gt;Crystalline World; pg 48",
      "name": "",
      "_key": "!tables.results!CxL6KGVQkI4zB1YM.NNIqcHIujesDlsUK"
    },
    {
      "range": [
        24,
        41
      ],
      "_id": "Z0h5av9ufmFfmMjL",
      "type": "text",
      "img": "icons/dice/d10black.svg",
      "weight": 1,
      "drawn": false,
      "flags": {},
      "_stats": {
        "coreVersion": "13.351",
        "systemId": null,
        "systemVersion": null,
        "createdTime": null,
        "modifiedTime": null,
        "lastModifiedBy": null,
        "compendiumSource": null,
        "duplicateSource": null,
        "exportSource": null
      },
      "description": "&gt;Desert World; pg 50",
      "name": "",
      "_key": "!tables.results!CxL6KGVQkI4zB1YM.Z0h5av9ufmFfmMjL"
    },
    {
      "range": [
        42,
        56
      ],
      "_id": "DxxTH6Y8dVdYVcmo",
      "type": "text",
      "img": "icons/dice/d10black.svg",
      "weight": 1,
      "drawn": false,
      "flags": {},
      "_stats": {
        "coreVersion": "13.351",
        "systemId": null,
        "systemVersion": null,
        "createdTime": null,
        "modifiedTime": null,
        "lastModifiedBy": null,
        "compendiumSource": null,
        "duplicateSource": null,
        "exportSource": null
      },
      "description": "&gt;Tainted World; pg 76",
      "name": "",
      "_key": "!tables.results!CxL6KGVQkI4zB1YM.DxxTH6Y8dVdYVcmo"
    },
    {
      "range": [
        57,
        68
      ],
      "_id": "uNVjdd7oDzMjygs8",
      "type": "text",
      "img": "icons/dice/d10black.svg",
      "weight": 1,
      "drawn": false,
      "flags": {},
      "_stats": {
        "coreVersion": "13.351",
        "systemId": null,
        "systemVersion": null,
        "createdTime": null,
        "modifiedTime": null,
        "lastModifiedBy": null,
        "compendiumSource": null,
        "duplicateSource": null,
        "exportSource": null
      },
      "description": "&gt;Jungle World; pg 60",
      "name": "",
      "_key": "!tables.results!CxL6KGVQkI4zB1YM.uNVjdd7oDzMjygs8"
    },
    {
      "range": [
        69,
        77
      ],
      "_id": "18gE48rLT51PI7Yv",
      "type": "text",
      "img": "icons/dice/d10black.svg",
      "weight": 1,
      "drawn": false,
      "flags": {},
      "_stats": {
        "coreVersion": "13.351",
        "systemId": null,
        "systemVersion": null,
        "createdTime": null,
        "modifiedTime": null,
        "lastModifiedBy": null,
        "compendiumSource": null,
        "duplicateSource": null,
        "exportSource": null
      },
      "description": "&gt;Vital World; pg 80",
      "name": "",
      "_key": "!tables.results!CxL6KGVQkI4zB1YM.18gE48rLT51PI7Yv"
    },
    {
      "range": [
        78,
        85
      ],
      "_id": "P4Jb7L2ogP7CgGT4",
      "type": "text",
      "img": "icons/dice/d10black.svg",
      "weight": 1,
      "drawn": false,
      "flags": {},
      "_stats": {
        "coreVersion": "13.351",
        "systemId": null,
        "systemVersion": null,
        "createdTime": null,
        "modifiedTime": null,
        "lastModifiedBy": null,
        "compendiumSource": null,
        "duplicateSource": null,
        "exportSource": null
      },
      "description": "&gt;Grave World; pg 54",
      "name": "",
      "_key": "!tables.results!CxL6KGVQkI4zB1YM.P4Jb7L2ogP7CgGT4"
    },
    {
      "range": [
        86,
        92
      ],
      "_id": "tbUCv4DJfDwrtSIZ",
      "type": "text",
      "img": "icons/dice/d10black.svg",
      "weight": 1,
      "drawn": false,
      "flags": {},
      "_stats": {
        "coreVersion": "13.351",
        "systemId": null,
        "systemVersion": null,
        "createdTime": null,
        "modifiedTime": null,
        "lastModifiedBy": null,
        "compendiumSource": null,
        "duplicateSource": null,
        "exportSource": null
      },
      "description": "&gt;Ocean World; pg 70",
      "name": "",
      "_key": "!tables.results!CxL6KGVQkI4zB1YM.tbUCv4DJfDwrtSIZ"
    },
    {
      "range": [
        93,
        97
      ],
      "_id": "xix7lS6jEPYWY928",
      "type": "text",
      "img": "icons/dice/d10black.svg",
      "weight": 1,
      "drawn": false,
      "flags": {},
      "_stats": {
        "coreVersion": "13.351",
        "systemId": null,
        "systemVersion": null,
        "createdTime": null,
        "modifiedTime": null,
        "lastModifiedBy": null,
        "compendiumSource": null,
        "duplicateSource": null,
        "exportSource": null
      },
      "description": "&gt;Ice World; pg 56",
      "name": "",
      "_key": "!tables.results!CxL6KGVQkI4zB1YM.xix7lS6jEPYWY928"
    },
    {
      "range": [
        98,
        100
      ],
      "_id": "BDYmVEOmm0akkxgx",
      "type": "text",
      "img": "icons/dice/d10black.svg",
      "weight": 1,
      "drawn": false,
      "flags": {},
      "_stats": {
        "coreVersion": "13.351",
        "systemId": null,
        "systemVersion": null,
        "createdTime": null,
        "modifiedTime": null,
        "lastModifiedBy": null,
        "compendiumSource": null,
        "duplicateSource": null,
        "exportSource": null
      },
      "description": "&gt;Chemical World; pg 46",
      "name": "",
      "_key": "!tables.results!CxL6KGVQkI4zB1YM.BDYmVEOmm0akkxgx"
    }
  ],
  "folder": "qfQdoESUXOJpkJnW",
  "sort": 3,
  "_id": "CxL6KGVQkI4zB1YM",
  "img": "icons/svg/d20-grey.svg",
  "replacement": true,
  "displayRoll": true,
  "ownership": {
    "default": 0,
    "MmM06BuCrG9h1GLg": 3
  },
  "flags": {},
  "_stats": {
    "compendiumSource": null,
    "duplicateSource": null,
    "coreVersion": "13.351",
    "systemId": "foundry-ironsworn",
    "systemVersion": "1.25.1",
    "createdTime": 1745457524452,
    "modifiedTime": 1745457524452,
    "lastModifiedBy": "MmM06BuCrG9h1GLg",
    "exportSource": null
  },
  "_key": "!tables!CxL6KGVQkI4zB1YM"
}
